tests/__init__.py
written/__init__.py
written/__main__.py
written/errors/__init__.py
written/misc/__init__.py
written/sync/__init__.py
written-0.0.3.dist-info/LICENSE
written-0.0.3.dist-info/METADATA
written-0.0.3.dist-info/WHEEL
written-0.0.3.dist-info/entry_points.txt
written-0.0.3.dist-info/top_level.txt
written-0.0.3.dist-info/RECORD
