Metadata-Version: 2.1
Name: written
Version: 0.0.3
Summary: Try to atomically write data to a file
Home-page: https://github.com/pyrustic/written
Author: Pyrustic Evangelist
Author-email: rusticalex@yahoo.com
Maintainer: Pyrustic Evangelist
Maintainer-email: rusticalex@yahoo.com
License: MIT
Keywords: application,pyrustic
Platform: UNKNOWN
Classifier: Programming Language :: Python :: 3
Classifier: License :: OSI Approved :: MIT License
Classifier: Operating System :: OS Independent
Requires-Python: >=3.5
License-File: LICENSE
